legaltext/__init__.py
legaltext/actions.py
legaltext/admin.py
legaltext/apps.py
legaltext/fields.py
legaltext/models.py
legaltext/urls.py
legaltext/utils.py
legaltext/views.py
legaltext/widgets.py
legaltext/locale/de/LC_MESSAGES/django.mo
legaltext/locale/de/LC_MESSAGES/django.po
legaltext/migrations/0001_initial.py
legaltext/migrations/0002_legaltextcheckbox.py
legaltext/migrations/0003_legaltext_url_name.py
legaltext/migrations/0004_auto_20170913_0714.py
legaltext/migrations/0005_auto_20170922_0723.py
legaltext/migrations/__init__.py
legaltext/templates/legaltext/content.html
legaltext/templates/legaltext/widget.html
legaltext/templatetags/__init__.py
legaltext/templatetags/legaltext_tags.py
django_legaltext-1.0.0.dist-info/LICENSE.rst
django_legaltext-1.0.0.dist-info/METADATA
django_legaltext-1.0.0.dist-info/WHEEL
django_legaltext-1.0.0.dist-info/top_level.txt
django_legaltext-1.0.0.dist-info/RECORD
