Metadata-Version: 2.1
Name: django-legaltext
Version: 1.0.0
Summary: django-legaltext helps to manage legal text versioning.
Home-page: https://github.com/moccu/django-legaltext/
Author: Moccu GmbH & Co. KG
Author-email: info@moccu.com
License: BSD
Keywords: legaltext,django
Platform: UNKNOWN
Classifier: Environment :: Web Environment
Classifier: Intended Audience :: Developers
Classifier: License :: OSI Approved :: Apache Software License
Classifier: Operating System :: OS Independent
Classifier: Topic :: Software Development :: Libraries :: Python Modules
Classifier: Framework :: Django
Classifier: Framework :: Django :: 1.9
Classifier: Framework :: Django :: 1.10
Classifier: Framework :: Django :: 1.11
Classifier: Programming Language :: Python
Classifier: Programming Language :: Python :: 2
Classifier: Programming Language :: Python :: 2.7
Classifier: Programming Language :: Python :: 3
Classifier: Programming Language :: Python :: 3.4
Classifier: Programming Language :: Python :: 3.5
Requires-Dist: Django (>=2)
Requires-Dist: django-floppyforms (>=1.8)
Requires-Dist: django-markymark (>=2.0)
Provides-Extra: tests
Requires-Dist: pytest (<5.4,>=5.3) ; extra == 'tests'
Requires-Dist: pytest-cov (<3,>=2.8.1) ; extra == 'tests'
Requires-Dist: pytest-django (<4,>=3.9.0) ; extra == 'tests'
Requires-Dist: pytest-flakes (<5,>=4.0.0) ; extra == 'tests'
Requires-Dist: pytest-isort (<1,>=0.3.1) ; extra == 'tests'
Requires-Dist: pytest-pep8 (<2,>=1.0.6) ; extra == 'tests'
Requires-Dist: factory-boy (<3,==2.12.0) ; extra == 'tests'
Requires-Dist: freezegun (<1,>=0.3.15) ; extra == 'tests'
Requires-Dist: isort (<4.4,>=4.3.21) ; extra == 'tests'
Requires-Dist: coverage (>=4.0) ; extra == 'tests'
Requires-Dist: tox ; extra == 'tests'
Requires-Dist: tox-pyenv ; extra == 'tests'
